farsa/__init__.py
farsa/exception.py
farsa/pattern.py
Farsa-0.1.dist-info/METADATA
Farsa-0.1.dist-info/WHEEL
Farsa-0.1.dist-info/top_level.txt
Farsa-0.1.dist-info/RECORD
