Metadata-Version: 2.1
Name: Farsa
Version: 0.1
Summary: UNKNOWN
Home-page: https://github.com/nyaoouo/Farsa
Author: Nyaoouo
Author-email: x@y.z
License: GPLv3
Platform: UNKNOWN
Requires-Dist: pefile (~=2021.9.3)
